hypervector.py
hypervector-0.1.0.dist-info/METADATA
hypervector-0.1.0.dist-info/WHEEL
hypervector-0.1.0.dist-info/top_level.txt
hypervector-0.1.0.dist-info/RECORD
