Metadata-Version: 2.1
Name: hypervector
Version: 0.1.0
Summary: Simple, general, pure Python vectors
Home-page: https://github.com/benburrill/hypervector
Author: Ben Burrill
Author-email: bburrill98+hypervector@gmail.com
License: Public Domain
Platform: any
Classifier: Programming Language :: Python :: 3
Classifier: Operating System :: OS Independent
Classifier: Topic :: Scientific/Engineering :: Mathematics
Classifier: License :: Public Domain
